README.rst
setup.py
coolwait/__init__.py
coolwait/warna.py
coolwait.egg-info/PKG-INFO
coolwait.egg-info/SOURCES.txt
coolwait.egg-info/dependency_links.txt
coolwait.egg-info/top_level.txt