Metadata-Version: 2.1
Name: coolwait
Version: 0.5
Summary: my first project on pypi
Home-page: https://github.com/kang-newbie/colorwait
Author: Noobie
Author-email: adlizhafari122@gmail.com
License: MIT
Keywords: COOLWAIT,COLORWAIT
Platform: UNKNOWN
Classifier: Development Status :: 3 - Alpha
Classifier: Intended Audience :: Developers
Classifier: Topic :: Software Development :: Build Tools
Classifier: License :: OSI Approved :: MIT License
Classifier: Programming Language :: Python :: 3
Requires-Python: >=3
